tmr0.v
module tmr0(
    input wire oscIn,
    input wire t0cki,
    input wire t0cs,
    input wire t0se,
    input wire reset,
    input wire [2:0] ps,
    input wire psa,
    output reg tmr0out,
    output reg t0if,
    output reg clkout
);
    reg [7:0] prescaler;
    reg clk;

    always @ * begin
        if (t0cs) begin
            clk = t0cki ^ t0se;
        end else begin
            clk = oscIn;
        end
        
    end

    always @(posedge clk) begin
        if(!reset) begin
            prescaler <= 8'b0;
        end else if (prescaler == 8'b11111111) begin
            prescaler <= 8'b0;
        end else begin
            prescaler <= prescaler + 1;
        end
    end

    always @ * begin
        if(psa) begin
            clkout = clk;
        end else begin
            clkout = prescaler[ps];
        end
    end

endmodule

tb.v
`include "tmr0.v"

module tb;
    reg oscIn;
    reg t0cki;
    reg t0cs;
    reg t0se;
    reg reset;
    reg psa;
    reg [2:0] ps;
    wire tmr0out;
    wire t0if;

tmr0 uut(
    .oscIn(oscIn),
    .t0cki(t0cki),
    .t0cs(t0cs),
    .t0se(t0se),
    .reset(reset),
    .ps(ps),
    .psa(psa),
    .tmr0out(tmr0out),
    .t0if(t0if)
);

always #5 oscIn = ~oscIn;

initial begin
    $dumpfile("tb.vcd");
    $dumpvars(0, tb);
    reset = 0;
    oscIn = 0;
    t0cki = 0;
    t0cs = 0;
    t0se = 0;
    psa = 0;
    ps = 1;

    #10 reset = 1;

    repeat(100) @(posedge oscIn);
    $finish;
end
endmodule

tb.vcd
$date
	Sat May 25 15:51:07 2024
$end
$version
	Icarus Verilog
$end
$timescale
	1s
$end
$scope module tb $end
$var wire 1 ! t0if $end
$var wire 1 " tmr0out $end
$var reg 1 # oscIn $end
$var reg 3 $ ps [2:0] $end
$var reg 1 % psa $end
$var reg 1 & reset $end
$var reg 1 ' t0cki $end
$var reg 1 ( t0cs $end
$var reg 1 ) t0se $end
$scope module uut $end
$var wire 1 * oscIn $end
$var wire 3 + ps [2:0] $end
$var wire 1 , psa $end
$var wire 1 - reset $end
$var wire 1 . t0cki $end
$var wire 1 / t0cs $end
$var wire 1 0 t0se $end
$var reg 1 1 clk $end
$var reg 1 2 clkout $end
$var reg 8 3 prescaler [7:0] $end
$var reg 1 4 t0if $end
$var reg 1 5 tmr0out $end
$upscope $end
$upscope $end
$enddefinitions $end
#0
$dumpvars
x5
x4
bx 3
x2
01
00
0/
0.
0-
0,
b1 +
0*
0)
0(
0'
0&
0%
b1 $
0#
x"
x!
$end
#5
02
b0 3
11
1#
1*
#10
01
0#
0*
1&
1-
#15
b1 3
11
1#
1*
#20
01
0#
0*
#25
12
b10 3
11
1#
1*
#30
01
0#
0*
#35
b11 3
11
1#
1*
#40
01
0#
0*
#45
02
b100 3
11
1#
1*
#50
01
0#
0*
#55
b101 3
11
1#
1*
#60
01
0#
0*
#65
12
b110 3
11
1#
1*
#70
01
0#
0*
#75
b111 3
11
1#
1*
#80
01
0#
0*
#85
02
b1000 3
11
1#
1*
#90
01
0#
0*
#95
b1001 3
11
1#
1*
#100
01
0#
0*
#105
12
b1010 3
11
1#
1*
#110
01
0#
0*
#115
b1011 3
11
1#
1*
#120
01
0#
0*
#125
02
b1100 3
11
1#
1*
#130
01
0#
0*
#135
b1101 3
11
1#
1*
#140
01
0#
0*
#145
12
b1110 3
11
1#
1*
#150
01
0#
0*
#155
b1111 3
11
1#
1*
#160
01
0#
0*
#165
02
b10000 3
11
1#
1*
#170
01
0#
0*
#175
b10001 3
11
1#
1*
#180
01
0#
0*
#185
12
b10010 3
11
1#
1*
#190
01
0#
0*
#195
b10011 3
11
1#
1*
#200
01
0#
0*
#205
02
b10100 3
11
1#
1*
#210
01
0#
0*
#215
b10101 3
11
1#
1*
#220
01
0#
0*
#225
12
b10110 3
11
1#
1*
#230
01
0#
0*
#235
b10111 3
11
1#
1*
#240
01
0#
0*
#245
02
b11000 3
11
1#
1*
#250
01
0#
0*
#255
b11001 3
11
1#
1*
#260
01
0#
0*
#265
12
b11010 3
11
1#
1*
#270
01
0#
0*
#275
b11011 3
11
1#
1*
#280
01
0#
0*
#285
02
b11100 3
11
1#
1*
#290
01
0#
0*
#295
b11101 3
11
1#
1*
#300
01
0#
0*
#305
12
b11110 3
11
1#
1*
#310
01
0#
0*
#315
b11111 3
11
1#
1*
#320
01
0#
0*
#325
02
b100000 3
11
1#
1*
#330
01
0#
0*
#335
b100001 3
11
1#
1*
#340
01
0#
0*
#345
12
b100010 3
11
1#
1*
#350
01
0#
0*
#355
b100011 3
11
1#
1*
#360
01
0#
0*
#365
02
b100100 3
11
1#
1*
#370
01
0#
0*
#375
b100101 3
11
1#
1*
#380
01
0#
0*
#385
12
b100110 3
11
1#
1*
#390
01
0#
0*
#395
b100111 3
11
1#
1*
#400
01
0#
0*
#405
02
b101000 3
11
1#
1*
#410
01
0#
0*
#415
b101001 3
11
1#
1*
#420
01
0#
0*
#425
12
b101010 3
11
1#
1*
#430
01
0#
0*
#435
b101011 3
11
1#
1*
#440
01
0#
0*
#445
02
b101100 3
11
1#
1*
#450
01
0#
0*
#455
b101101 3
11
1#
1*
#460
01
0#
0*
#465
12
b101110 3
11
1#
1*
#470
01
0#
0*
#475
b101111 3
11
1#
1*
#480
01
0#
0*
#485
02
b110000 3
11
1#
1*
#490
01
0#
0*
#495
b110001 3
11
1#
1*
#500
01
0#
0*
#505
12
b110010 3
11
1#
1*
#510
01
0#
0*
#515
b110011 3
11
1#
1*
#520
01
0#
0*
#525
02
b110100 3
11
1#
1*
#530
01
0#
0*
#535
b110101 3
11
1#
1*
#540
01
0#
0*
#545
12
b110110 3
11
1#
1*
#550
01
0#
0*
#555
b110111 3
11
1#
1*
#560
01
0#
0*
#565
02
b111000 3
11
1#
1*
#570
01
0#
0*
#575
b111001 3
11
1#
1*
#580
01
0#
0*
#585
12
b111010 3
11
1#
1*
#590
01
0#
0*
#595
b111011 3
11
1#
1*
#600
01
0#
0*
#605
02
b111100 3
11
1#
1*
#610
01
0#
0*
#615
b111101 3
11
1#
1*
#620
01
0#
0*
#625
12
b111110 3
11
1#
1*
#630
01
0#
0*
#635
b111111 3
11
1#
1*
#640
01
0#
0*
#645
02
b1000000 3
11
1#
1*
#650
01
0#
0*
#655
b1000001 3
11
1#
1*
#660
01
0#
0*
#665
12
b1000010 3
11
1#
1*
#670
01
0#
0*
#675
b1000011 3
11
1#
1*
#680
01
0#
0*
#685
02
b1000100 3
11
1#
1*
#690
01
0#
0*
#695
b1000101 3
11
1#
1*
#700
01
0#
0*
#705
12
b1000110 3
11
1#
1*
#710
01
0#
0*
#715
b1000111 3
11
1#
1*
#720
01
0#
0*
#725
02
b1001000 3
11
1#
1*
#730
01
0#
0*
#735
b1001001 3
11
1#
1*
#740
01
0#
0*
#745
12
b1001010 3
11
1#
1*
#750
01
0#
0*
#755
b1001011 3
11
1#
1*
#760
01
0#
0*
#765
02
b1001100 3
11
1#
1*
#770
01
0#
0*
#775
b1001101 3
11
1#
1*
#780
01
0#
0*
#785
12
b1001110 3
11
1#
1*
#790
01
0#
0*
#795
b1001111 3
11
1#
1*
#800
01
0#
0*
#805
02
b1010000 3
11
1#
1*
#810
01
0#
0*
#815
b1010001 3
11
1#
1*
#820
01
0#
0*
#825
12
b1010010 3
11
1#
1*
#830
01
0#
0*
#835
b1010011 3
11
1#
1*
#840
01
0#
0*
#845
02
b1010100 3
11
1#
1*
#850
01
0#
0*
#855
b1010101 3
11
1#
1*
#860
01
0#
0*
#865
12
b1010110 3
11
1#
1*
#870
01
0#
0*
#875
b1010111 3
11
1#
1*
#880
01
0#
0*
#885
02
b1011000 3
11
1#
1*
#890
01
0#
0*
#895
b1011001 3
11
1#
1*
#900
01
0#
0*
#905
12
b1011010 3
11
1#
1*
#910
01
0#
0*
#915
b1011011 3
11
1#
1*
#920
01
0#
0*
#925
02
b1011100 3
11
1#
1*
#930
01
0#
0*
#935
b1011101 3
11
1#
1*
#940
01
0#
0*
#945
12
b1011110 3
11
1#
1*
#950
01
0#
0*
#955
b1011111 3
11
1#
1*
#960
01
0#
0*
#965
02
b1100000 3
11
1#
1*
#970
01
0#
0*
#975
b1100001 3
11
1#
1*
#980
01
0#
0*
#985
12
b1100010 3
11
1#
1*
#990
01
0#
0*
#995
b1100011 3
11
1#
1*
#1000
01
0#
0*
#1005
02
b1100100 3
11
1#
1*
